Metadata-Version: 2.1
Name: odoo10-addon-shopinvader-locomotive
Version: 10.0.1.1.0
Summary: Manage communications between Shopinvader and Locomotive CMS
Home-page: http://www.akretion.com
Author: Akretion
License: AGPL-3
Platform: UNKNOWN
Classifier: Programming Language :: Python
Classifier: Framework :: Odoo
Classifier: License :: OSI Approved :: GNU Affero General Public License v3
Requires-Python: ~=2.7
Requires-Dist: locomotivecms
Requires-Dist: odoo10-addon-base-suspend-security
Requires-Dist: odoo10-addon-connector
Requires-Dist: odoo10-addon-keychain
Requires-Dist: odoo10-addon-queue-job
Requires-Dist: odoo10-addon-shopinvader
Requires-Dist: odoo (<10.1dev,>=10.0)
Requires-Dist: openupgradelib
